livekit/plugins/n8n/__init__.py
livekit/plugins/n8n/llm.py
livekit/plugins/n8n/log.py
livekit/plugins/n8n/version.py
livekit_plugins_n8n-0.1.0.dist-info/licenses/LICENSE
livekit_plugins_n8n-0.1.0.dist-info/METADATA
livekit_plugins_n8n-0.1.0.dist-info/WHEEL
livekit_plugins_n8n-0.1.0.dist-info/top_level.txt
livekit_plugins_n8n-0.1.0.dist-info/RECORD
