Metadata-Version: 2.4
Name: livekit-plugins-n8n
Version: 0.1.0
Summary: LiveKit plugin for integrating n8n webhooks with voice AI agents
Author-email: Haitham Ramadan <haithamramadan5001@gmail.com>
License: Apache-2.0
Project-URL: Homepage, https://github.com/yourusername/livekit-plugins-n8n
Project-URL: Documentation, https://github.com/yourusername/livekit-plugins-n8n#readme
Project-URL: Repository, https://github.com/yourusername/livekit-plugins-n8n
Project-URL: Issues, https://github.com/yourusername/livekit-plugins-n8n/issues
Keywords: livekit,n8n,webhook,voice-ai,agents,llm
Classifier: Development Status :: 4 - Beta
Classifier: Intended Audience :: Developers
Classifier: License :: OSI Approved :: Apache Software License
Classifier: Programming Language :: Python :: 3
Classifier: Programming Language :: Python :: 3.9
Classifier: Programming Language :: Python :: 3.10
Classifier: Programming Language :: Python :: 3.11
Classifier: Programming Language :: Python :: 3.12
Classifier: Topic :: Software Development :: Libraries :: Python Modules
Classifier: Topic :: Communications :: Chat
Requires-Python: >=3.9
License-File: LICENSE
Requires-Dist: livekit-agents>=0.8.0
Requires-Dist: aiohttp>=3.9.0
Dynamic: license-file
